{
    "id": "drama",
    "name": "Drama",
    "movies": [
      {
        "id": "7",
        "title": "The Shawshank Redemption",
        "release_year": 1994,
        "poster_image": "https://www.themoviedb.org/t/p/w600_and_h900_bestv2/q6y0Go1tsGEsmtFryDOJo3dEmqu.jpg"
      },
      {
        "id": "8",
        "title": "Forrest Gump",
        "release_year": 1994,
        "poster_image": "https://www.themoviedb.org/t/p/w600_and_h900_bestv2/yE5d3BUhE8hCnkMUJOo1QDoOGNz.jpg"
      },
      {
        "id": "9",
        "title": "The Godfather",
        "release_year": 1972,
        "poster_image": "https://www.themoviedb.org/t/p/w600_and_h900_bestv2/3bhkrj58Vtu7enYsRolD1fZdja1.jpg"
      }
    ]
  }